bookleter/Booklet.py
bookleter/__init__.py
bookleter/__main__.py
bookleter/gui.py
bookleter/shuffle.py
bookleter-0.8.3.dist-info/licenses/LICENSE
bookleter-0.8.3.dist-info/METADATA
bookleter-0.8.3.dist-info/WHEEL
bookleter-0.8.3.dist-info/entry_points.txt
bookleter-0.8.3.dist-info/top_level.txt
bookleter-0.8.3.dist-info/RECORD
