Metadata-Version: 2.4
Name: bookleter
Version: 0.8.3
Summary: Turns pdfs into a6 sized foldable booklets
Author-email: Mohsen Barzegar <2.mohsenbarzegar@gmail.com>
License-Expression: MIT
Project-URL: HomePage, https://github.com/sehraramiz/bookleter
Keywords: booklet,A6
Requires-Python: >=3.10
License-File: LICENSE
Requires-Dist: pdfcropmargins>=2.2.1
Requires-Dist: pdfrw>=0.4
Requires-Dist: pillow>=12.0.0
Requires-Dist: pypdf2>=3.0.1
Dynamic: license-file
